<annotation>
  <filename>Patient01631_Plane3_1_of_2.png</filename>
  <folder></folder>
  <source>
    <sourceImage></sourceImage>
    <sourceAnnotation>Datumaro</sourceAnnotation>
  </source>
  <imagesize>
    <nrows>661</nrows>
    <ncols>959</ncols>
  </imagesize>
  <object>
    <name>CSP</name>
    <deleted>0</deleted>
    <verified>0</verified>
    <occluded>no</occluded>
    <date></date>
    <id>0</id>
    <parts>
      <hasparts></hasparts>
      <ispartof></ispartof>
    </parts>
    <type>bounding_box</type>
    <polygon>
      <pt>
        <x>345.58</x>
        <y>294.65</y>
      </pt>
      <pt>
        <x>460.89</x>
        <y>294.65</y>
      </pt>
      <pt>
        <x>460.89</x>
        <y>327.17</y>
      </pt>
      <pt>
        <x>345.58</x>
        <y>327.17</y>
      </pt>
      <username></username>
    </polygon>
    <attributes>rotation=187.10000000000002</attributes>
  </object>
  <object>
    <name>LV</name>
    <deleted>0</deleted>
    <verified>0</verified>
    <occluded>no</occluded>
    <date></date>
    <id>1</id>
    <parts>
      <hasparts></hasparts>
      <ispartof></ispartof>
    </parts>
    <type>bounding_box</type>
    <polygon>
      <pt>
        <x>672.45</x>
        <y>335.64</y>
      </pt>
      <pt>
        <x>793.45</x>
        <y>335.64</y>
      </pt>
      <pt>
        <x>793.45</x>
        <y>413.55</y>
      </pt>
      <pt>
        <x>672.45</x>
        <y>413.55</y>
      </pt>
      <username></username>
    </polygon>
    <attributes>rotation=340.1</attributes>
  </object>
</annotation>
