<annotation>
  <filename>Patient00964_Plane3_1_of_4.png</filename>
  <folder></folder>
  <source>
    <sourceImage></sourceImage>
    <sourceAnnotation>Datumaro</sourceAnnotation>
  </source>
  <imagesize>
    <nrows>661</nrows>
    <ncols>959</ncols>
  </imagesize>
  <object>
    <name>CSP</name>
    <deleted>0</deleted>
    <verified>0</verified>
    <occluded>no</occluded>
    <date></date>
    <id>0</id>
    <parts>
      <hasparts></hasparts>
      <ispartof></ispartof>
    </parts>
    <type>bounding_box</type>
    <polygon>
      <pt>
        <x>472.45</x>
        <y>244.60</y>
      </pt>
      <pt>
        <x>536.79</x>
        <y>244.60</y>
      </pt>
      <pt>
        <x>536.79</x>
        <y>278.81</y>
      </pt>
      <pt>
        <x>472.45</x>
        <y>278.81</y>
      </pt>
      <username></username>
    </polygon>
    <attributes>rotation=6.5</attributes>
  </object>
  <object>
    <name>Brain</name>
    <deleted>0</deleted>
    <verified>0</verified>
    <occluded>no</occluded>
    <date></date>
    <id>1</id>
    <parts>
      <hasparts></hasparts>
      <ispartof></ispartof>
    </parts>
    <segm>
      <mask>Patient00964_Plane3_1_of_4_mask_1.png</mask>
      <box>
        <xmin>298.00</xmin>
        <ymin>35.00</ymin>
        <xmax>896.00</xmax>
        <ymax>513.00</ymax>
      </box>
      <username></username>
    </segm>
    <attributes>age=, weight=, pixel_size=</attributes>
  </object>
  <object>
    <name>LV</name>
    <deleted>0</deleted>
    <verified>0</verified>
    <occluded>no</occluded>
    <date></date>
    <id>2</id>
    <parts>
      <hasparts></hasparts>
      <ispartof></ispartof>
    </parts>
    <type>bounding_box</type>
    <polygon>
      <pt>
        <x>694.52</x>
        <y>348.19</y>
      </pt>
      <pt>
        <x>788.49</x>
        <y>348.19</y>
      </pt>
      <pt>
        <x>788.49</x>
        <y>406.43</y>
      </pt>
      <pt>
        <x>694.52</x>
        <y>406.43</y>
      </pt>
      <username></username>
    </polygon>
    <attributes>rotation=349.4</attributes>
  </object>
</annotation>
