<annotation>
  <filename>Patient01712_Plane3_1_of_5.png</filename>
  <folder></folder>
  <source>
    <sourceImage></sourceImage>
    <sourceAnnotation>Datumaro</sourceAnnotation>
  </source>
  <imagesize>
    <nrows>661</nrows>
    <ncols>959</ncols>
  </imagesize>
  <object>
    <name>CSP</name>
    <deleted>0</deleted>
    <verified>0</verified>
    <occluded>no</occluded>
    <date></date>
    <id>0</id>
    <parts>
      <hasparts></hasparts>
      <ispartof></ispartof>
    </parts>
    <type>bounding_box</type>
    <polygon>
      <pt>
        <x>453.12</x>
        <y>225.31</y>
      </pt>
      <pt>
        <x>519.90</x>
        <y>225.31</y>
      </pt>
      <pt>
        <x>519.90</x>
        <y>254.09</y>
      </pt>
      <pt>
        <x>453.12</x>
        <y>254.09</y>
      </pt>
      <username></username>
    </polygon>
    <attributes>rotation=0.0</attributes>
  </object>
  <object>
    <name>LV</name>
    <deleted>0</deleted>
    <verified>0</verified>
    <occluded>no</occluded>
    <date></date>
    <id>1</id>
    <parts>
      <hasparts></hasparts>
      <ispartof></ispartof>
    </parts>
    <type>bounding_box</type>
    <polygon>
      <pt>
        <x>602.40</x>
        <y>292.39</y>
      </pt>
      <pt>
        <x>714.04</x>
        <y>292.39</y>
      </pt>
      <pt>
        <x>714.04</x>
        <y>356.93</y>
      </pt>
      <pt>
        <x>602.40</x>
        <y>356.93</y>
      </pt>
      <username></username>
    </polygon>
    <attributes>rotation=343.9</attributes>
  </object>
  <object>
    <name>Brain</name>
    <deleted>0</deleted>
    <verified>0</verified>
    <occluded>no</occluded>
    <date></date>
    <id>2</id>
    <parts>
      <hasparts></hasparts>
      <ispartof></ispartof>
    </parts>
    <segm>
      <mask>Patient01712_Plane3_1_of_5_mask_2.png</mask>
      <box>
        <xmin>283.00</xmin>
        <ymin>37.00</ymin>
        <xmax>831.00</xmax>
        <ymax>447.00</ymax>
      </box>
      <username></username>
    </segm>
    <attributes>age=, weight=, pixel_size=</attributes>
  </object>
</annotation>
