<annotation>
  <filename>Patient01786_Plane3_2_of_3.png</filename>
  <folder></folder>
  <source>
    <sourceImage></sourceImage>
    <sourceAnnotation>Datumaro</sourceAnnotation>
  </source>
  <imagesize>
    <nrows>661</nrows>
    <ncols>959</ncols>
  </imagesize>
  <object>
    <name>Brain</name>
    <deleted>0</deleted>
    <verified>0</verified>
    <occluded>no</occluded>
    <date></date>
    <id>0</id>
    <parts>
      <hasparts></hasparts>
      <ispartof></ispartof>
    </parts>
    <segm>
      <mask>Patient01786_Plane3_2_of_3_mask_0.png</mask>
      <box>
        <xmin>65.00</xmin>
        <ymin>37.00</ymin>
        <xmax>697.00</xmax>
        <ymax>559.00</ymax>
      </box>
      <username></username>
    </segm>
    <attributes>age=, weight=, pixel_size=</attributes>
  </object>
  <object>
    <name>LV</name>
    <deleted>0</deleted>
    <verified>0</verified>
    <occluded>no</occluded>
    <date></date>
    <id>1</id>
    <parts>
      <hasparts></hasparts>
      <ispartof></ispartof>
    </parts>
    <type>bounding_box</type>
    <polygon>
      <pt>
        <x>239.88</x>
        <y>385.56</y>
      </pt>
      <pt>
        <x>334.33</x>
        <y>385.56</y>
      </pt>
      <pt>
        <x>334.33</x>
        <y>447.29</y>
      </pt>
      <pt>
        <x>239.88</x>
        <y>447.29</y>
      </pt>
      <username></username>
    </polygon>
    <attributes>rotation=4.90000000000002</attributes>
  </object>
</annotation>
